{"keywords": [{"relevance": 0.934905, "text": "Parties", "emotion": {"anger": 0.156635, "joy": 0.30657, "sadness": 0.166001, "fear": 0.136108, "disgust": 0.172375}, "sentiment": {"score": 0.118249}}, {"relevance": 0.737936, "text": "protocol", "emotion": {"anger": 0.169638, "joy": 0.254363, "sadness": 0.208863, "fear": 0.154269, "disgust": 0.176335}, "sentiment": {"score": 0.124546}}, {"relevance": 0.666338, "text": "Article", "emotion": {"anger": 0.178515, "joy": 0.229601, "sadness": 0.264448, "fear": 0.149211, "disgust": 0.133837}, "sentiment": {"score": -0.0230316}}, {"relevance": 0.536435, "text": "climate change", "emotion": {"anger": 0.184867, "joy": 0.195046, "sadness": 0.553113, "fear": 0.133919, "disgust": 0.148075}, "sentiment": {"score": 0.225714}}, {"relevance": 0.521142, "text": "annex", "emotion": {"anger": 0.152252, "joy": 0.277469, "sadness": 0.204498, "fear": 0.170748, "disgust": 0.148755}, "sentiment": {"score": -0.118434}}, {"relevance": 0.510535, "text": "Conference", "emotion": {"anger": 0.166166, "joy": 0.310169, "sadness": 0.137619, "fear": 0.128139, "disgust": 0.194954}, "sentiment": {"score": 0.19061}}, {"relevance": 0.481596, "text": "convention", "emotion": {"anger": 0.167669, "joy": 0.262184, "sadness": 0.213205, "fear": 0.135278, "disgust": 0.466692}, "sentiment": {"score": 0.140188}}, {"relevance": 0.459589, "text": "party", "emotion": {"anger": 0.133191, "joy": 0.284273, "sadness": 0.187783, "fear": 0.160276, "disgust": 0.184793}, "sentiment": {"score": 0.0379841}}, {"relevance": 0.41133, "text": "meeting", "emotion": {"anger": 0.172042, "joy": 0.336064, "sadness": 0.134942, "fear": 0.112467, "disgust": 0.170849}, "sentiment": {"score": 0.162927}}, {"relevance": 0.380981, "text": "paragraph", "emotion": {"anger": 0.168541, "joy": 0.201601, "sadness": 0.299539, "fear": 0.15662, "disgust": 0.139785}, "sentiment": {"score": -0.0326216}}, {"relevance": 0.380569, "text": "commitment period", "emotion": {"anger": 0.142873, "joy": 0.202729, "sadness": 0.246321, "fear": 0.248989, "disgust": 0.139471}, "sentiment": {"score": 0.143085}}, {"relevance": 0.375211, "text": "greenhouse gases", "emotion": {"anger": 0.166376, "joy": 0.13404, "sadness": 0.310432, "fear": 0.196577, "disgust": 0.232323}, "sentiment": {"score": -0.435575}}, {"relevance": 0.356764, "text": "commitments", "emotion": {"anger": 0.151787, "joy": 0.499759, "sadness": 0.252235, "fear": 0.155254, "disgust": 0.134373}, "sentiment": {"score": 0.0217469}}, {"relevance": 0.354738, "text": "Subsidiary Body", "emotion": {"anger": 0.203942, "joy": 0.148379, "sadness": 0.191639, "fear": 0.156155, "disgust": 0.47982}, "sentiment": {"score": 0.394172}}, {"relevance": 0.34602, "text": "regional economic integration", "emotion": {"anger": 0.092316, "joy": 0.405388, "sadness": 0.172703, "fear": 0.100658, "disgust": 0.12192}, "sentiment": {"score": 0.385159}}, {"relevance": 0.339027, "text": "clean development mechanism", "emotion": {"anger": 0.144507, "joy": 0.52024, "sadness": 0.123766, "fear": 0.070316, "disgust": 0.277538}, "sentiment": {"score": 0.573988}}, {"relevance": 0.333926, "text": "accordance", "emotion": {"anger": 0.168084, "joy": 0.255503, "sadness": 0.242939, "fear": 0.139964, "disgust": 0.147094}, "sentiment": {"score": 0.414619}}, {"relevance": 0.333684, "text": "relevant decisions", "emotion": {"anger": 0.203709, "joy": 0.247039, "sadness": 0.233352, "fear": 0.105355, "disgust": 0.161284}, "sentiment": {"score": 0.546106}}, {"relevance": 0.331466, "text": "implementation", "emotion": {"anger": 0.15094, "joy": 0.234736, "sadness": 0.225341, "fear": 0.14191, "disgust": 0.446633}, "sentiment": {"score": 0.479967}}, {"relevance": 0.327442, "text": "emission reduction units", "emotion": {"anger": 0.195765, "joy": 0.179549, "sadness": 0.280203, "fear": 0.196446, "disgust": 0.126593}, "sentiment": {"score": 0.0}}, {"relevance": 0.314793, "text": "united nations", "emotion": {"anger": 0.240031, "joy": 0.21879, "sadness": 0.254172, "fear": 0.097065, "disgust": 0.152873}, "sentiment": {"score": 0.0}}, {"relevance": 0.310626, "text": "emissions", "emotion": {"anger": 0.192246, "joy": 0.173924, "sadness": 0.278543, "fear": 0.176699, "disgust": 0.204026}, "sentiment": {"score": -0.00419068}}, {"relevance": 0.309559, "text": "Technological Advice", "emotion": {"anger": 0.210443, "joy": 0.140796, "sadness": 0.199557, "fear": 0.150854, "disgust": 0.484285}, "sentiment": {"score": 0.367478}}, {"relevance": 0.308914, "text": "Montreal Protocol", "emotion": {"anger": 0.181991, "joy": 0.098902, "sadness": 0.505533, "fear": 0.198673, "disgust": 0.246864}, "sentiment": {"score": -0.435575}}, {"relevance": 0.305808, "text": "country Parties", "emotion": {"anger": 0.106276, "joy": 0.272649, "sadness": 0.50339, "fear": 0.06625, "disgust": 0.231391}, "sentiment": {"score": 0.825875}}, {"relevance": 0.297641, "text": "greenhouse gas emissions", "emotion": {"anger": 0.188944, "joy": 0.447948, "sadness": 0.270049, "fear": 0.183732, "disgust": 0.239508}, "sentiment": {"score": -0.105843}}, {"relevance": 0.295516, "text": "emission limitation", "emotion": {"anger": 0.171519, "joy": 0.19204, "sadness": 0.313256, "fear": 0.170344, "disgust": 0.122841}, "sentiment": {"score": 0.130641}}, {"relevance": 0.294415, "text": "session", "emotion": {"anger": 0.173331, "joy": 0.347379, "sadness": 0.107453, "fear": 0.145503, "disgust": 0.150559}, "sentiment": {"score": 0.0399428}}, {"relevance": 0.287761, "text": "emission reductions", "emotion": {"anger": 0.118165, "joy": 0.316157, "sadness": 0.209306, "fear": 0.124471, "disgust": 0.171769}, "sentiment": {"score": 0.119787}}, {"relevance": 0.287396, "text": "Intergovernmental Panel", "emotion": {"anger": 0.188057, "joy": 0.183207, "sadness": 0.285993, "fear": 0.134926, "disgust": 0.190457}, "sentiment": {"score": 0.32113}}, {"relevance": 0.285713, "text": "aggregate anthropogenic carbon", "emotion": {"anger": 0.082109, "joy": 0.178044, "sadness": 0.396566, "fear": 0.11426, "disgust": 0.177205}, "sentiment": {"score": -0.464993}}, {"relevance": 0.285431, "text": "dioxide equivalent emissions", "emotion": {"anger": 0.082109, "joy": 0.178044, "sadness": 0.396566, "fear": 0.11426, "disgust": 0.177205}, "sentiment": {"score": -0.464993}}, {"relevance": 0.284565, "text": "carbon dioxide", "emotion": {"anger": 0.160347, "joy": 0.228991, "sadness": 0.257229, "fear": 0.129425, "disgust": 0.183823}, "sentiment": {"score": -0.464993}}, {"relevance": 0.284236, "text": "anthropogenic carbon dioxide", "emotion": {"anger": 0.082109, "joy": 0.178044, "sadness": 0.396566, "fear": 0.11426, "disgust": 0.177205}, "sentiment": {"score": -0.464993}}, {"relevance": 0.283737, "text": "environmentally sound technologies", "emotion": {"anger": 0.375857, "joy": 0.160296, "sadness": 0.141015, "fear": 0.088587, "disgust": 0.278402}, "sentiment": {"score": 0.0}}, {"relevance": 0.283716, "text": "reduction commitments", "emotion": {"anger": 0.171081, "joy": 0.205197, "sadness": 0.302274, "fear": 0.160224, "disgust": 0.122712}, "sentiment": {"score": 0.130641}}, {"relevance": 0.283288, "text": "certified emission reductions", "emotion": {"anger": 0.070859, "joy": 0.510974, "sadness": 0.08578, "fear": 0.041871, "disgust": 0.178194}, "sentiment": {"score": 0.339836}}, {"relevance": 0.28244, "text": "nations framework convention", "emotion": {"anger": 0.530958, "joy": 0.197402, "sadness": 0.06967, "fear": 0.027433, "disgust": 0.171327}, "sentiment": {"score": 0.0}}, {"relevance": 0.281213, "text": "information", "emotion": {"anger": 0.138192, "joy": 0.226498, "sadness": 0.590949, "fear": 0.107802, "disgust": 0.071225}, "sentiment": {"score": 0.502903}}, {"relevance": 0.280699, "text": "united nations framework", "emotion": {"anger": 0.530958, "joy": 0.197402, "sadness": 0.06967, "fear": 0.027433, "disgust": 0.171327}, "sentiment": {"score": 0.0}}, {"relevance": 0.278392, "text": "account", "emotion": {"anger": 0.263356, "joy": 0.123285, "sadness": 0.606206, "fear": 0.09613, "disgust": 0.10767}, "sentiment": {"score": 0.533735}}, {"relevance": 0.276844, "text": "economic integration organization", "emotion": {"anger": 0.060705, "joy": 0.549206, "sadness": 0.115438, "fear": 0.04858, "disgust": 0.107062}, "sentiment": {"score": 0.254542}}, {"relevance": 0.270068, "text": "quantified emission limitation", "emotion": {"anger": 0.171519, "joy": 0.19204, "sadness": 0.313256, "fear": 0.170344, "disgust": 0.122841}, "sentiment": {"score": -0.297222}}, {"relevance": 0.26545, "text": "provisions", "emotion": {"anger": 0.177564, "joy": 0.234975, "sadness": 0.249728, "fear": 0.13386, "disgust": 0.446954}, "sentiment": {"score": 0.4255}}, {"relevance": 0.262465, "text": "mutatis mutandis", "emotion": {"anger": 0.118922, "joy": 0.311915, "sadness": 0.141545, "fear": 0.16684, "disgust": 0.180136}, "sentiment": {"score": 0.0}}, {"relevance": 0.262257, "text": "anthropogenic emissions", "emotion": {"anger": 0.165629, "joy": 0.074961, "sadness": 0.52215, "fear": 0.218493, "disgust": 0.289229}, "sentiment": {"score": -0.435575}}, {"relevance": 0.26165, "text": "secretariat", "emotion": {"anger": 0.166572, "joy": 0.273916, "sadness": 0.224763, "fear": 0.12322, "disgust": 0.142138}, "sentiment": {"score": 0.439708}}, {"relevance": 0.260597, "text": "account Article", "emotion": {"anger": 0.420091, "joy": 0.08367, "sadness": 0.407542, "fear": 0.062219, "disgust": 0.079509}, "sentiment": {"score": 0.2135}}, {"relevance": 0.258304, "text": "amendment", "emotion": {"anger": 0.158339, "joy": 0.24519, "sadness": 0.246202, "fear": 0.161337, "disgust": 0.145659}, "sentiment": {"score": 0.517605}}, {"relevance": 0.256229, "text": "developed country Parties", "emotion": {"anger": 0.071679, "joy": 0.146682, "sadness": 0.375514, "fear": 0.032444, "disgust": 0.36152}, "sentiment": {"score": 0.0}}], "warnings": ["truncated-oversized-text-content"], "language": "en", "retrieved_url": "http://bruchansky.name/wp-content/uploads/2017/03/kyoto-protocol.txt"}